{
    "swagger": "2.0",
    "info": {
        "contact": {}
    },
    "paths": {
        "/employees": {
            "get": {
                "description": "Get details of all employees",
                "produces": [
                    "application/json"
                ],
                "summary": "Get all employees",
                "responses": {
                    "200": {
                        "description": "OK",
                        "schema": {
                            "type": "array",
                            "items": {
                                "$ref": "#/definitions/model.Employee"
                            }
                        }
                    }
                }
            }
        }
    },
    "definitions": {
        "model.Employee": {
            "type": "object",
            "properties": {
                "id": {
                    "type": "integer"
                },
                "name": {
                    "type": "string"
                },
                "position": {
                    "type": "string"
                },
                "salary": {
                    "type": "integer"
                }
            }
        }
    }
}